informationtracer/__init__.py
informationtracer/informationtracer.py
informationtracer-0.1.4.dist-info/LICENSE
informationtracer-0.1.4.dist-info/METADATA
informationtracer-0.1.4.dist-info/WHEEL
informationtracer-0.1.4.dist-info/top_level.txt
informationtracer-0.1.4.dist-info/RECORD
