Metadata-Version: 2.1
Name: informationtracer
Version: 0.1.4
Summary: Client-side API to access Information Tracer
Home-page: https://github.com/zhouhanc/informationtracer
Author: Zhouhan Chen
Author-email: zhouhan.chen@nyu.edu
License: BSD 2-clause
Classifier: Development Status :: 1 - Planning
Classifier: Intended Audience :: Science/Research
Classifier: License :: OSI Approved :: BSD License
Classifier: Programming Language :: Python :: 2
Classifier: Programming Language :: Python :: 2.7
Classifier: Programming Language :: Python :: 3
Classifier: Programming Language :: Python :: 3.4
Classifier: Programming Language :: Python :: 3.5
License-File: LICENSE
Requires-Dist: requests
